spark_job_tracker.py
spark_job_tracker-0.0.1.dist-info/LICENSE
spark_job_tracker-0.0.1.dist-info/METADATA
spark_job_tracker-0.0.1.dist-info/WHEEL
spark_job_tracker-0.0.1.dist-info/top_level.txt
spark_job_tracker-0.0.1.dist-info/RECORD
