Metadata-Version: 2.1
Name: spark-job-tracker
Version: 0.0.1
Summary: Spark Job Tracking
Home-page: UNKNOWN
Author: Rahul Kumar
Author-email: rahulcomp24@gmail.com
License: UNKNOWN
Platform: UNKNOWN
Classifier: Programming Language :: Python :: 3
Classifier: License :: OSI Approved :: MIT License
Classifier: Operating System :: OS Independent
Requires-Python: >=3.6
